{
    "endOfGameResult": "GameComplete",
    "gameCreation": 1711403564000,
    "gameId": 4956438414,
    "game_datetime": 1711405952559,
    "game_length": 2370.140625,
    "game_version": "Version 14.6.569.5139 (Mar 20 2024/15:26:11) [PUBLIC] <Releases/14.6>",
    "mapId": 22,
    "participants": [
        {
            "augments": [
                "TFT9_Augment_KnowYourEnemy",
                "TFT6_Augment_Recombobulator",
                "TFT8_Augment_SalvageBinPlus"
            ],
            "companion": {
                "content_ID": "127829e1-6a49-45f7-b59d-f63c3f8b6e58",
                "item_ID": 49003,
                "skin_ID": 3,
                "species": "PetChibiAhri"
            },
            "gold_left": 1,
            "last_round": 40,
            "level": 9,
            "missions": {
                "Assists": 0,
                "DamageDealt": 0,
                "DamageDealtToObjectives": 81311,
                "DamageDealtToTurrets": 4,
                "DamageTaken": 0,
                "Deaths": 18,
                "DoubleKills": 0,
                "GoldEarned": 0,
                "GoldSpent": 0,
                "InhibitorsDestroyed": 0,
                "KillingSprees": 16,
                "Kills": 0,
                "LargestKillingSpree": 60481,
                "LargestMultiKill": 273658,
                "MagicDamageDealt": 0,
                "MagicDamageDealtToChampions": 0,
                "MagicDamageTaken": 0,
                "NeutralMinionsKilledTeamJungle": 0,
                "PentaKills": 1,
                "PhysicalDamageDealt": 0,
                "PhysicalDamageDealtToChampions": 27,
                "PhysicalDamageTaken": 2,
                "PlayerScore0": 3,
                "PlayerScore1": 7,
                "PlayerScore10": 0,
                "PlayerScore11": 0,
                "PlayerScore2": 229,
                "PlayerScore3": 0,
                "PlayerScore4": 1,
                "PlayerScore5": 1,
                "PlayerScore6": 10,
                "PlayerScore9": 0,
                "QuadraKills": 0,
                "Spell1Casts": 0,
                "Spell2Casts": 1,
                "Spell3Casts": 0,
                "Spell4Casts": 9573,
                "SummonerSpell1Casts": 0,
                "TimeCCOthers": 1,
                "TotalDamageDealtToChampions": 0,
                "TotalMinionsKilled": 0,
                "TripleKills": 0,
                "TrueDamageDealt": 1,
                "TrueDamageDealtToChampions": 55,
                "TrueDamageTaken": 8,
                "UnrealKills": 1,
                "VisionScore": 1,
                "WardsKilled": 61
            },
            "placement": 3,
            "players_eliminated": 0,
            "puuid": "MZMoaJI1r7L3B-RbibwGPrzUUD6tnZUwNKfH_UZtL-pjCcY0pAMHJu4scPWtvjC3JLTq6zUYo_zHXQ",
            "time_eliminated": 2295.3916015625,
            "total_damage_to_players": 155,
            "traits": [
                {
                    "name": "TFT11_Altruist",
                    "num_units": 3,
                    "style": 2,
                    "tier_current": 2,
                    "tier_total": 3
                },
                {
                    "name": "TFT11_Bruiser",
                    "num_units": 2,
                    "style": 1,
                    "tier_current": 1,
                    "tier_total": 4
                },
                {
                    "name": "TFT11_Dragonlord",
                    "num_units": 3,
                    "style": 2,
                    "tier_current": 2,
                    "tier_total": 4
                },
                {
                    "name": "TFT11_Duelist",
                    "num_units": 2,
                    "style": 1,
                    "tier_current": 1,
                    "tier_total": 4
                },
                {
                    "name": "TFT11_Great",
                    "num_units": 1,
                    "style": 5,
                    "tier_current": 1,
                    "tier_total": 1
                },
                {
                    "name": "TFT11_Heavenly",
                    "num_units": 2,
                    "style": 1,
                    "tier_current": 1,
                    "tier_total": 6
                },
                {
                    "name": "TFT11_Lovers",
                    "num_units": 1,
                    "style": 5,
                    "tier_current": 1,
                    "tier_total": 1
                },
                {
                    "name": "TFT11_Sage",
                    "num_units": 3,
                    "style": 2,
                    "tier_current": 2,
                    "tier_total": 4
                },
                {
                    "name": "TFT11_Storyweaver",
                    "num_units": 5,
                    "style": 2,
                    "tier_current": 2,
                    "tier_total": 4
                }
            ],
            "units": [
                {
                    "character_id": "TFT11_Riven",
                    "itemNames": [],
                    "name": "",
                    "rarity": 1,
                    "tier": 2
                },
                {
                    "character_id": "TFT11_Zyra",
                    "itemNames": [],
                    "name": "",
                    "rarity": 1,
                    "tier": 2
                },
                {
                    "character_id": "TFT11_Soraka",
                    "itemNames": [],
                    "name": "",
                    "rarity": 2,
                    "tier": 2
                },
                {
                    "character_id": "TFT11_Diana",
                    "itemNames": [
                        "TFT_Item_GargoyleStoneplate",
                        "TFT_Item_NightHarvester"
                    ],
                    "name": "",
                    "rarity": 2,
                    "tier": 2
                },
                {
                    "character_id": "TFT11_Galio",
                    "itemNames": [
                        "TFT_Item_GargoyleStoneplate",
                        "TFT_Item_NightHarvester",
                        "TFT_Item_Redemption"
                    ],
                    "name": "",
                    "rarity": 4,
                    "tier": 2
                },
                {
                    "character_id": "TFT11_LeeSin",
                    "itemNames": [
                        "TFT11_Item_StoryweaverEmblemItem"
                    ],
                    "name": "",
                    "rarity": 4,
                    "tier": 2
                },
                {
                    "character_id": "TFT11_Irelia",
                    "itemNames": [
                        "TFT_Item_InfinityEdge",
                        "TFT_Item_Deathblade",
                        "TFT_Item_GuinsoosRageblade"
                    ],
                    "name": "",
                    "rarity": 6,
                    "tier": 2
                },
                {
                    "character_id": "TFT11_Rakan",
                    "itemNames": [
                        "TFT_Item_TitansResolve",
                        "TFT_Item_Morellonomicon"
                    ],
                    "name": "",
                    "rarity": 6,
                    "tier": 1
                },
                {
                    "character_id": "TFT11_WuKong",
                    "itemNames": [
                        "TFT_Item_TitansResolve"
                    ],
                    "name": "",
                    "rarity": 6,
                    "tier": 2
                },
                {
                    "character_id": "TFT11_Kayle",
                    "itemNames": [
                        "TFT11_Storyweaver5_AS",
                        "TFT11_Storyweaver3_Support"
                    ],
                    "name": "",
                    "rarity": 9,
                    "tier": 2
                }
            ]
        },
        {
            "augments": [
                "TFT9_Augment_ACutAbove",
                "TFT10_Augment_SilverVeil",
                "TFT10_Augment_HeroicGrabBag"
            ],
            "companion": {
                "content_ID": "b890d4df-181a-43da-861d-99a72afbc602",
                "item_ID": 38002,
                "skin_ID": 2,
                "species": "PetChibiYasuo"
            },
            "gold_left": 3,
            "last_round": 28,
            "level": 8,
            "missions": {
                "Assists": 0,
                "DamageDealt": 0,
                "DamageDealtToObjectives": 22240,
                "DamageDealtToTurrets": 4,
                "DamageTaken": 0,
                "Deaths": 0,
                "DoubleKills": 0,
                "GoldEarned": 0,
                "GoldSpent": 0,
                "InhibitorsDestroyed": 0,
                "KillingSprees": 9,
                "Kills": 0,
                "LargestKillingSpree": 23131,
                "LargestMultiKill": 131438,
                "MagicDamageDealt": 0,
                "MagicDamageDealtToChampions": 0,
                "MagicDamageTaken": 0,
                "NeutralMinionsKilledTeamJungle": 0,
                "PentaKills": 0,
                "PhysicalDamageDealt": 0,
                "PhysicalDamageDealtToChampions": 20,
                "PhysicalDamageTaken": 0,
                "PlayerScore0": 5,
                "PlayerScore1": 6,
                "PlayerScore10": 0,
                "PlayerScore11": 0,
                "PlayerScore2": 81,
                "PlayerScore3": 0,
                "PlayerScore4": 1,
                "PlayerScore5": 1,
                "PlayerScore6": 16,
                "PlayerScore9": 0,
                "QuadraKills": 0,
                "Spell1Casts": 0,
                "Spell2Casts": 0,
                "Spell3Casts": 0,
                "Spell4Casts": 800,
                "SummonerSpell1Casts": 0,
                "TimeCCOthers": 1,
                "TotalDamageDealtToChampions": 0,
                "TotalMinionsKilled": 0,
                "TripleKills": 0,
                "TrueDamageDealt": 1,
                "TrueDamageDealtToChampions": 45,
                "TrueDamageTaken": 6,
                "UnrealKills": 1,
                "VisionScore": 1,
                "WardsKilled": 64
            },
            "placement": 5,
            "players_eliminated": 0,
            "puuid": "z3-mUbrfdgPw1dl0dm9XSDx_1JDNy31Ei3W20nCLGPn756QJChkOptNz9gZk64AwouSyv4VwEvzOOw",
            "time_eliminated": 1634.8309326171875,
            "total_damage_to_players": 56,
            "traits": [
                {
                    "name": "TFT11_Altruist",
                    "num_units": 2,
                    "style": 1,
                    "tier_current": 1,
                    "tier_total": 3
                },
                {
                    "name": "TFT11_Dragonlord",
                    "num_units": 2,
                    "style": 1,
                    "tier_current": 1,
                    "tier_total": 4
                },
                {
                    "name": "TFT11_Duelist",
                    "num_units": 6,
                    "style": 3,
                    "tier_current": 3,
                    "tier_total": 4
                },
                {
                    "name": "TFT11_Exalted",
                    "num_units": 1,
                    "style": 0,
                    "tier_current": 0,
                    "tier_total": 2
                },
                {
                    "name": "TFT11_Fated",
                    "num_units": 1,
                    "style": 0,
                    "tier_current": 0,
                    "tier_total": 4
                },
                {
                    "name": "TFT11_Fortune",
                    "num_units": 1,
                    "style": 0,
                    "tier_current": 0,
                    "tier_total": 3
                },
                {
                    "name": "TFT11_Heavenly",
                    "num_units": 3,
                    "style": 2,
                    "tier_current": 2,
                    "tier_total": 6
                },
                {
                    "name": "TFT11_InkShadow",
                    "num_units": 1,
                    "style": 0,
                    "tier_current": 0,
                    "tier_total": 3
                },
                {
                    "name": "TFT11_Lovers",
                    "num_units": 1,
                    "style": 5,
                    "tier_current": 1,
                    "tier_total": 1
                },
                {
                    "name": "TFT11_Umbral",
                    "num_units": 1,
                    "style": 0,
                    "tier_current": 0,
                    "tier_total": 4
                }
            ],
            "units": [
                {
                    "character_id": "TFT11_Darius",
                    "itemNames": [],
                    "name": "",
                    "rarity": 0,
                    "tier": 2
                },
                {
                    "character_id": "TFT11_Yasuo",
                    "itemNames": [
                        "TFT11_Item_HeavenlyEmblemItem"
                    ],
                    "name": "",
                    "rarity": 0,
                    "tier": 2
                },
                {
                    "character_id": "TFT11_Qiyana",
                    "itemNames": [],
                    "name": "",
                    "rarity": 1,
                    "tier": 2
                },
                {
                    "character_id": "TFT11_Volibear",
                    "itemNames": [
                        "TFT_Item_SpectralGauntlet",
                        "TFT_Item_GargoyleStoneplate"
                    ],
                    "name": "",
                    "rarity": 2,
                    "tier": 3
                },
                {
                    "character_id": "TFT11_Soraka",
                    "itemNames": [
                        "TFT_Item_NeedlesslyLargeRod"
                    ],
                    "name": "",
                    "rarity": 2,
                    "tier": 2
                },
                {
                    "character_id": "TFT11_Tristana",
                    "itemNames": [
                        "TFT_Item_Deathblade",
                        "TFT_Item_GuinsoosRageblade",
                        "TFT_Item_InfinityEdge"
                    ],
                    "name": "",
                    "rarity": 2,
                    "tier": 3
                },
                {
                    "character_id": "TFT11_LeeSin",
                    "itemNames": [
                        "TFT_Item_TitansResolve"
                    ],
                    "name": "",
                    "rarity": 4,
                    "tier": 1
                },
                {
                    "character_id": "TFT11_Rakan",
                    "itemNames": [],
                    "name": "",
                    "rarity": 6,
                    "tier": 1
                }
            ]
        },
        {
            "augments": [
                "TFT9_Augment_JeweledLotus",
                "TFT9_Augment_Formation1",
                "TFT6_Augment_PortableForgePlusPlus"
            ],
            "companion": {
                "content_ID": "6d88e0ca-1b9d-4e2c-bd71-46988f601c65",
                "item_ID": 7020,
                "skin_ID": 20,
                "species": "PetGemTiger"
            },
            "gold_left": 2,
            "last_round": 27,
            "level": 8,
            "missions": {
                "Assists": 0,
                "DamageDealt": 0,
                "DamageDealtToObjectives": 95554,
                "DamageDealtToTurrets": 4,
                "DamageTaken": 0,
                "Deaths": 0,
                "DoubleKills": 0,
                "GoldEarned": 0,
                "GoldSpent": 0,
                "InhibitorsDestroyed": 0,
                "KillingSprees": 4,
                "Kills": 0,
                "LargestKillingSpree": 5134,
                "LargestMultiKill": 51539,
                "MagicDamageDealt": 0,
                "MagicDamageDealtToChampions": 0,
                "MagicDamageTaken": 0,
                "NeutralMinionsKilledTeamJungle": 0,
                "PentaKills": 0,
                "PhysicalDamageDealt": 0,
                "PhysicalDamageDealtToChampions": 18,
                "PhysicalDamageTaken": 0,
                "PlayerScore0": 6,
                "PlayerScore1": 6,
                "PlayerScore10": 0,
                "PlayerScore11": 0,
                "PlayerScore2": 78,
                "PlayerScore3": 0,
                "PlayerScore4": 1,
                "PlayerScore5": 1,
                "PlayerScore6": 8,
                "PlayerScore9": 0,
                "QuadraKills": 0,
                "Spell1Casts": 0,
                "Spell2Casts": 4,
                "Spell3Casts": 0,
                "Spell4Casts": 3794,
                "SummonerSpell1Casts": 0,
                "TimeCCOthers": 0,
                "TotalDamageDealtToChampions": 0,
                "TotalMinionsKilled": 0,
                "TripleKills": 0,
                "TrueDamageDealt": 1,
                "TrueDamageDealtToChampions": 51,
                "TrueDamageTaken": 6,
                "UnrealKills": 0,
                "VisionScore": 0,
                "WardsKilled": 62
            },
            "placement": 6,
            "players_eliminated": 1,
            "puuid": "geMcnfDiYIKavL0dFEV3iWBQbm04SaCzaGtaLUwpU2nKhDN8P8gRRm1imYxINh-TA8TUngCYJTNPxA",
            "time_eliminated": 1578.5601806640625,
            "total_damage_to_players": 54,
            "traits": [
                {
                    "name": "TFT11_Arcanist",
                    "num_units": 2,
                    "style": 1,
                    "tier_current": 1,
                    "tier_total": 4
                },
                {
                    "name": "TFT11_Behemoth",
                    "num_units": 3,
                    "style": 1,
                    "tier_current": 1,
                    "tier_total": 3
                },
                {
                    "name": "TFT11_Dryad",
                    "num_units": 2,
                    "style": 1,
                    "tier_current": 1,
                    "tier_total": 3
                },
                {
                    "name": "TFT11_Fated",
                    "num_units": 7,
                    "style": 3,
                    "tier_current": 3,
                    "tier_total": 4
                },
                {
                    "name": "TFT11_InkShadow",
                    "num_units": 1,
                    "style": 0,
                    "tier_current": 0,
                    "tier_total": 3
                },
                {
                    "name": "TFT11_Reaper",
                    "num_units": 1,
                    "style": 0,
                    "tier_current": 0,
                    "tier_total": 2
                },
                {
                    "name": "TFT11_Sniper",
                    "num_units": 1,
                    "style": 0,
                    "tier_current": 0,
                    "tier_total": 3
                },
                {
                    "name": "TFT11_SpiritWalker",
                    "num_units": 1,
                    "style": 5,
                    "tier_current": 1,
                    "tier_total": 1
                },
                {
                    "name": "TFT11_Umbral",
                    "num_units": 1,
                    "style": 0,
                    "tier_current": 0,
                    "tier_total": 4
                },
                {
                    "name": "TFT11_Warden",
                    "num_units": 1,
                    "style": 0,
                    "tier_current": 0,
                    "tier_total": 3
                }
            ],
            "units": [
                {
                    "character_id": "TFT11_Ahri",
                    "itemNames": [],
                    "name": "",
                    "rarity": 0,
                    "tier": 2
                },
                {
                    "character_id": "TFT11_Kindred",
                    "itemNames": [],
                    "name": "",
                    "rarity": 1,
                    "tier": 1
                },
                {
                    "character_id": "TFT11_Aphelios",
                    "itemNames": [],
                    "name": "",
                    "rarity": 2,
                    "tier": 2
                },
                {
                    "character_id": "TFT11_Thresh",
                    "itemNames": [
                        "TFT_Item_RedBuff",
                        "TFT_Item_FrozenHeart",
                        "TFT_Item_AdaptiveHelm"
                    ],
                    "name": "",
                    "rarity": 2,
                    "tier": 2
                },
                {
                    "character_id": "TFT11_Ornn",
                    "itemNames": [],
                    "name": "",
                    "rarity": 4,
                    "tier": 2
                },
                {
                    "character_id": "TFT11_Syndra",
                    "itemNames": [
                        "TFT9_Item_OrnnDeathfireGrasp",
                        "TFT_Item_AdaptiveHelm",
                        "TFT_Item_UnstableConcoction"
                    ],
                    "name": "",
                    "rarity": 4,
                    "tier": 2
                },
                {
                    "character_id": "TFT11_Sett",
                    "itemNames": [],
                    "name": "",
                    "rarity": 6,
                    "tier": 1
                },
                {
                    "character_id": "TFT11_Udyr",
                    "itemNames": [
                        "TFT11_Item_FatedEmblemItem"
                    ],
                    "name": "",
                    "rarity": 6,
                    "tier": 1
                }
            ]
        },
        {
            "augments": [
                "TFT9_Augment_LearningFromExperience2",
                "TFT_Augment_BranchingOut",
                "TFT9_Augment_HealingOrbsII"
            ],
            "companion": {
                "content_ID": "3422ad41-bd41-4e7c-a9fe-068b0c80e730",
                "item_ID": 71018,
                "skin_ID": 18,
                "species": "PetSmolKnifeDog"
            },
            "gold_left": 0,
            "last_round": 26,
            "level": 8,
            "missions": {
                "Assists": 0,
                "DamageDealt": 0,
                "DamageDealtToObjectives": 84622,
                "DamageDealtToTurrets": 4,
                "DamageTaken": 0,
                "Deaths": 4,
                "DoubleKills": 0,
                "GoldEarned": 0,
                "GoldSpent": 0,
                "InhibitorsDestroyed": 0,
                "KillingSprees": 4,
                "Kills": 0,
                "LargestKillingSpree": 23628,
                "LargestMultiKill": 36579,
                "MagicDamageDealt": 0,
                "MagicDamageDealtToChampions": 0,
                "MagicDamageTaken": 0,
                "NeutralMinionsKilledTeamJungle": 0,
                "PentaKills": 1,
                "PhysicalDamageDealt": 0,
                "PhysicalDamageDealtToChampions": 19,
                "PhysicalDamageTaken": 0,
                "PlayerScore0": 7,
                "PlayerScore1": 6,
                "PlayerScore10": 0,
                "PlayerScore11": 0,
                "PlayerScore2": 75,
                "PlayerScore3": 0,
                "PlayerScore4": 1,
                "PlayerScore5": 1,
                "PlayerScore6": 9,
                "PlayerScore9": 0,
                "QuadraKills": 0,
                "Spell1Casts": 0,
                "Spell2Casts": 1,
                "Spell3Casts": 0,
                "Spell4Casts": 2679,
                "SummonerSpell1Casts": 0,
                "TimeCCOthers": 0,
                "TotalDamageDealtToChampions": 0,
                "TotalMinionsKilled": 0,
                "TripleKills": 0,
                "TrueDamageDealt": 1,
                "TrueDamageDealtToChampions": 56,
                "TrueDamageTaken": 6,
                "UnrealKills": 0,
                "VisionScore": 0,
                "WardsKilled": 65
            },
            "placement": 7,
            "players_eliminated": 0,
            "puuid": "KP6nf8tBfLCLyrir0EJgaYqVEQVSVCtySyXgR_p1L-O6HB8bIVuZ5jP8gLcE7z50lYYBBQ-3N_85ig",
            "time_eliminated": 1502.54736328125,
            "total_damage_to_players": 42,
            "traits": [
                {
                    "name": "TFT11_Bruiser",
                    "num_units": 2,
                    "style": 1,
                    "tier_current": 1,
                    "tier_total": 4
                },
                {
                    "name": "TFT11_Dryad",
                    "num_units": 1,
                    "style": 0,
                    "tier_current": 0,
                    "tier_total": 3
                },
                {
                    "name": "TFT11_Exalted",
                    "num_units": 2,
                    "style": 0,
                    "tier_current": 0,
                    "tier_total": 2
                },
                {
                    "name": "TFT11_Fated",
                    "num_units": 1,
                    "style": 0,
                    "tier_current": 0,
                    "tier_total": 4
                },
                {
                    "name": "TFT11_Invoker",
                    "num_units": 4,
                    "style": 2,
                    "tier_current": 2,
                    "tier_total": 3
                },
                {
                    "name": "TFT11_Mythic",
                    "num_units": 5,
                    "style": 2,
                    "tier_current": 2,
                    "tier_total": 4
                },
                {
                    "name": "TFT11_Porcelain",
                    "num_units": 1,
                    "style": 0,
                    "tier_current": 0,
                    "tier_total": 3
                },
                {
                    "name": "TFT11_Sniper",
                    "num_units": 1,
                    "style": 0,
                    "tier_current": 0,
                    "tier_total": 3
                },
                {
                    "name": "TFT11_Umbral",
                    "num_units": 3,
                    "style": 1,
                    "tier_current": 1,
                    "tier_total": 4
                },
                {
                    "name": "TFT11_Warden",
                    "num_units": 2,
                    "style": 1,
                    "tier_current": 1,
                    "tier_total": 3
                }
            ],
            "units": [
                {
                    "character_id": "TFT11_KogMaw",
                    "itemNames": [],
                    "name": "",
                    "rarity": 0,
                    "tier": 2
                },
                {
                    "character_id": "TFT11_Alune",
                    "itemNames": [],
                    "name": "",
                    "rarity": 2,
                    "tier": 2
                },
                {
                    "character_id": "TFT11_TahmKench",
                    "itemNames": [],
                    "name": "",
                    "rarity": 2,
                    "tier": 2
                },
                {
                    "character_id": "TFT11_Lillia",
                    "itemNames": [
                        "TFT11_Item_PorcelainEmblemItem"
                    ],
                    "name": "",
                    "rarity": 4,
                    "tier": 1
                },
                {
                    "character_id": "TFT11_Nautilus",
                    "itemNames": [
                        "TFT_Item_WarmogsArmor",
                        "TFT_Item_NightHarvester",
                        "TFT_Item_GargoyleStoneplate"
                    ],
                    "name": "",
                    "rarity": 4,
                    "tier": 2
                },
                {
                    "character_id": "TFT11_Sylas",
                    "itemNames": [
                        "TFT_Item_NegatronCloak"
                    ],
                    "name": "",
                    "rarity": 4,
                    "tier": 2
                },
                {
                    "character_id": "TFT11_Sett",
                    "itemNames": [],
                    "name": "",
                    "rarity": 6,
                    "tier": 1
                },
                {
                    "character_id": "TFT11_Azir",
                    "itemNames": [
                        "TFT_Item_SpearOfShojin",
                        "TFT11_Item_MythicEmblemItem",
                        "TFT_Item_JeweledGauntlet"
                    ],
                    "name": "",
                    "rarity": 6,
                    "tier": 2
                }
            ]
        },
        {
            "augments": [
                "TFT9_Augment_CombatCaster",
                "TFT9_Augment_MissedConnections",
                "TFT9_Augment_Commander_Ascension"
            ],
            "companion": {
                "content_ID": "6c2562ad-42ed-4578-9a12-63d27bf58c79",
                "item_ID": 55001,
                "skin_ID": 1,
                "species": "PetKoala"
            },
            "gold_left": 1,
            "last_round": 24,
            "level": 8,
            "missions": {
                "Assists": 0,
                "DamageDealt": 0,
                "DamageDealtToObjectives": 41672,
                "DamageDealtToTurrets": 4,
                "DamageTaken": 0,
                "Deaths": 0,
                "DoubleKills": 0,
                "GoldEarned": 0,
                "GoldSpent": 0,
                "InhibitorsDestroyed": 0,
                "KillingSprees": 3,
                "Kills": 0,
                "LargestKillingSpree": 8119,
                "LargestMultiKill": 63925,
                "MagicDamageDealt": 0,
                "MagicDamageDealtToChampions": 0,
                "MagicDamageTaken": 0,
                "NeutralMinionsKilledTeamJungle": 0,
                "PentaKills": 0,
                "PhysicalDamageDealt": 0,
                "PhysicalDamageDealtToChampions": 26,
                "PhysicalDamageTaken": 1,
                "PlayerScore0": 8,
                "PlayerScore1": 6,
                "PlayerScore10": 0,
                "PlayerScore11": 0,
                "PlayerScore2": 70,
                "PlayerScore3": 0,
                "PlayerScore4": 1,
                "PlayerScore5": 1,
                "PlayerScore6": 11,
                "PlayerScore9": 0,
                "QuadraKills": 0,
                "Spell1Casts": 0,
                "Spell2Casts": 1,
                "Spell3Casts": 0,
                "Spell4Casts": 1647,
                "SummonerSpell1Casts": 0,
                "TimeCCOthers": 0,
                "TotalDamageDealtToChampions": 0,
                "TotalMinionsKilled": 0,
                "TripleKills": 0,
                "TrueDamageDealt": 0,
                "TrueDamageDealtToChampions": 45,
                "TrueDamageTaken": 5,
                "UnrealKills": 0,
                "VisionScore": 0,
                "WardsKilled": 50
            },
            "placement": 8,
            "players_eliminated": 0,
            "puuid": "1hPNixRa60WQlxVPDqLAuEdr3Af1RZn2bMn4gv_tkmiC6hBtZ45GIhlUiB2ivF74BLgrDjdKBYnY0A",
            "time_eliminated": 1399.7008056640625,
            "total_damage_to_players": 29,
            "traits": [
                {
                    "name": "TFT11_Altruist",
                    "num_units": 1,
                    "style": 0,
                    "tier_current": 0,
                    "tier_total": 3
                },
                {
                    "name": "TFT11_Bruiser",
                    "num_units": 4,
                    "style": 2,
                    "tier_current": 2,
                    "tier_total": 4
                },
                {
                    "name": "TFT11_Exalted",
                    "num_units": 1,
                    "style": 0,
                    "tier_current": 0,
                    "tier_total": 2
                },
                {
                    "name": "TFT11_Fortune",
                    "num_units": 1,
                    "style": 0,
                    "tier_current": 0,
                    "tier_total": 3
                },
                {
                    "name": "TFT11_Ghostly",
                    "num_units": 1,
                    "style": 0,
                    "tier_current": 0,
                    "tier_total": 4
                },
                {
                    "name": "TFT11_InkShadow",
                    "num_units": 2,
                    "style": 0,
                    "tier_current": 0,
                    "tier_total": 3
                },
                {
                    "name": "TFT11_Mythic",
                    "num_units": 2,
                    "style": 0,
                    "tier_current": 0,
                    "tier_total": 4
                },
                {
                    "name": "TFT11_Storyweaver",
                    "num_units": 3,
                    "style": 1,
                    "tier_current": 1,
                    "tier_total": 4
                },
                {
                    "name": "TFT11_Trickshot",
                    "num_units": 4,
                    "style": 3,
                    "tier_current": 2,
                    "tier_total": 2
                }
            ],
            "units": [
                {
                    "character_id": "TFT11_Sivir",
                    "itemNames": [],
                    "name": "",
                    "rarity": 0,
                    "tier": 1
                },
                {
                    "character_id": "TFT11_Aatrox",
                    "itemNames": [],
                    "name": "",
                    "rarity": 1,
                    "tier": 2
                },
                {
                    "character_id": "TFT11_Riven",
                    "itemNames": [],
                    "name": "",
                    "rarity": 1,
                    "tier": 2
                },
                {
                    "character_id": "TFT11_Teemo",
                    "itemNames": [],
                    "name": "",
                    "rarity": 1,
                    "tier": 2
                },
                {
                    "character_id": "TFT11_Bard",
                    "itemNames": [],
                    "name": "",
                    "rarity": 2,
                    "tier": 2
                },
                {
                    "character_id": "TFT11_TahmKench",
                    "itemNames": [
                        "TFT_Item_FrozenHeart",
                        "TFT_Item_SpectralGauntlet"
                    ],
                    "name": "",
                    "rarity": 2,
                    "tier": 2
                },
                {
                    "character_id": "TFT11_Galio",
                    "itemNames": [],
                    "name": "",
                    "rarity": 4,
                    "tier": 1
                },
                {
                    "character_id": "TFT11_Kaisa",
                    "itemNames": [
                        "TFT_Item_InfinityEdge",
                        "TFT_Item_MadredsBloodrazor",
                        "TFT_Item_RunaansHurricane"
                    ],
                    "name": "",
                    "rarity": 4,
                    "tier": 1
                },
                {
                    "character_id": "TFT11_Kayle",
                    "itemNames": [
                        "TFT11_Storyweaver3_AS"
                    ],
                    "name": "",
                    "rarity": 9,
                    "tier": 1
                }
            ]
        },
        {
            "augments": [
                "TFT11_Augment_WanderingTrainerGold",
                "TFT7_Augment_BandOfThieves1",
                "TFT11_Augment_StoryweaverCrest"
            ],
            "companion": {
                "content_ID": "7b4009d4-1c30-4c39-ac6a-6e591e322d46",
                "item_ID": 27006,
                "skin_ID": 6,
                "species": "PetChoncc"
            },
            "gold_left": 1,
            "last_round": 41,
            "level": 9,
            "missions": {
                "Assists": 0,
                "DamageDealt": 0,
                "DamageDealtToObjectives": 190666,
                "DamageDealtToTurrets": 4,
                "DamageTaken": 0,
                "Deaths": 20,
                "DoubleKills": 0,
                "GoldEarned": 0,
                "GoldSpent": 0,
                "InhibitorsDestroyed": 1,
                "KillingSprees": 17,
                "Kills": 0,
                "LargestKillingSpree": 40589,
                "LargestMultiKill": 180170,
                "MagicDamageDealt": 0,
                "MagicDamageDealtToChampions": 0,
                "MagicDamageTaken": 0,
                "NeutralMinionsKilledTeamJungle": 0,
                "PentaKills": 0,
                "PhysicalDamageDealt": 0,
                "PhysicalDamageDealtToChampions": 25,
                "PhysicalDamageTaken": 3,
                "PlayerScore0": 2,
                "PlayerScore1": 7,
                "PlayerScore10": 0,
                "PlayerScore11": 0,
                "PlayerScore2": 236,
                "PlayerScore3": 0,
                "PlayerScore4": 1,
                "PlayerScore5": 1,
                "PlayerScore6": 15,
                "PlayerScore9": 0,
                "QuadraKills": 0,
                "Spell1Casts": 0,
                "Spell2Casts": 1,
                "Spell3Casts": 17,
                "Spell4Casts": 26360,
                "SummonerSpell1Casts": 0,
                "TimeCCOthers": 0,
                "TotalDamageDealtToChampions": 0,
                "TotalMinionsKilled": 0,
                "TripleKills": 0,
                "TrueDamageDealt": 1,
                "TrueDamageDealtToChampions": 75,
                "TrueDamageTaken": 6,
                "UnrealKills": 1,
                "VisionScore": 0,
                "WardsKilled": 87
            },
            "placement": 2,
            "players_eliminated": 2,
            "puuid": "g6UxNTG3pVWP5AWPw2PwYLK9Plqp1I7Y10f9L05tftu86kIO_XfUZ2WmrIVT96CAlJjg8scn_FEGig",
            "time_eliminated": 2361.84033203125,
            "total_damage_to_players": 154,
            "traits": [
                {
                    "name": "TFT11_Altruist",
                    "num_units": 3,
                    "style": 2,
                    "tier_current": 2,
                    "tier_total": 3
                },
                {
                    "name": "TFT11_Bruiser",
                    "num_units": 2,
                    "style": 1,
                    "tier_current": 1,
                    "tier_total": 4
                },
                {
                    "name": "TFT11_Dragonlord",
                    "num_units": 4,
                    "style": 2,
                    "tier_current": 3,
                    "tier_total": 4
                },
                {
                    "name": "TFT11_Duelist",
                    "num_units": 2,
                    "style": 1,
                    "tier_current": 1,
                    "tier_total": 4
                },
                {
                    "name": "TFT11_Ghostly",
                    "num_units": 2,
                    "style": 1,
                    "tier_current": 1,
                    "tier_total": 4
                },
                {
                    "name": "TFT11_Great",
                    "num_units": 1,
                    "style": 5,
                    "tier_current": 1,
                    "tier_total": 1
                },
                {
                    "name": "TFT11_Heavenly",
                    "num_units": 2,
                    "style": 1,
                    "tier_current": 1,
                    "tier_total": 6
                },
                {
                    "name": "TFT11_Lovers",
                    "num_units": 1,
                    "style": 5,
                    "tier_current": 1,
                    "tier_total": 1
                },
                {
                    "name": "TFT11_Sage",
                    "num_units": 3,
                    "style": 2,
                    "tier_current": 2,
                    "tier_total": 4
                },
                {
                    "name": "TFT11_Storyweaver",
                    "num_units": 5,
                    "style": 2,
                    "tier_current": 2,
                    "tier_total": 4
                }
            ],
            "units": [
                {
                    "character_id": "TFT11_Riven",
                    "itemNames": [],
                    "name": "",
                    "rarity": 1,
                    "tier": 2
                },
                {
                    "character_id": "TFT11_Soraka",
                    "itemNames": [],
                    "name": "",
                    "rarity": 2,
                    "tier": 1
                },
                {
                    "character_id": "TFT11_Diana",
                    "itemNames": [],
                    "name": "",
                    "rarity": 2,
                    "tier": 1
                },
                {
                    "character_id": "TFT11_Morgana",
                    "itemNames": [
                        "TFT_Item_Leviathan",
                        "TFT_Item_Morellonomicon",
                        "TFT_Item_SpearOfShojin"
                    ],
                    "name": "",
                    "rarity": 4,
                    "tier": 2
                },
                {
                    "character_id": "TFT11_Galio",
                    "itemNames": [
                        "TFT_Item_Crownguard",
                        "TFT_Item_NightHarvester",
                        "TFT_Item_GargoyleStoneplate"
                    ],
                    "name": "",
                    "rarity": 4,
                    "tier": 2
                },
                {
                    "character_id": "TFT11_LeeSin",
                    "itemNames": [
                        "TFT11_Item_StoryweaverEmblemItem"
                    ],
                    "name": "",
                    "rarity": 4,
                    "tier": 1
                },
                {
                    "character_id": "TFT11_Irelia",
                    "itemNames": [
                        "TFT_Item_GuinsoosRageblade",
                        "TFT_Item_Deathblade",
                        "TFT_Item_MadredsBloodrazor"
                    ],
                    "name": "",
                    "rarity": 6,
                    "tier": 2
                },
                {
                    "character_id": "TFT11_Rakan",
                    "itemNames": [
                        "TFT11_Item_StoryweaverEmblemItem",
                        "TFT_Item_GiantsBelt"
                    ],
                    "name": "",
                    "rarity": 6,
                    "tier": 2
                },
                {
                    "character_id": "TFT11_WuKong",
                    "itemNames": [
                        "TFT_Item_ThiefsGloves",
                        "TFT_Item_InfinityEdge",
                        "TFT_Item_RapidFireCannon"
                    ],
                    "name": "",
                    "rarity": 6,
                    "tier": 2
                },
                {
                    "character_id": "TFT11_Kayle",
                    "itemNames": [
                        "TFT11_Storyweaver5_AS",
                        "TFT11_Storyweaver3_Support"
                    ],
                    "name": "",
                    "rarity": 9,
                    "tier": 2
                }
            ]
        },
        {
            "augments": [
                "TFT9_Augment_BardPlaybook2",
                "TFT11_Augment_GoldenRemover",
                "TFT9_Augment_CyberneticBulk2"
            ],
            "companion": {
                "content_ID": "ef7ae41c-4571-4add-b267-346e6303d528",
                "item_ID": 17001,
                "skin_ID": 1,
                "species": "PetBuglet"
            },
            "gold_left": 2,
            "last_round": 41,
            "level": 9,
            "missions": {
                "Assists": 0,
                "DamageDealt": 0,
                "DamageDealtToObjectives": 112641,
                "DamageDealtToTurrets": 4,
                "DamageTaken": 0,
                "Deaths": 12,
                "DoubleKills": 0,
                "GoldEarned": 0,
                "GoldSpent": 0,
                "InhibitorsDestroyed": 0,
                "KillingSprees": 18,
                "Kills": 0,
                "LargestKillingSpree": 124775,
                "LargestMultiKill": 280344,
                "MagicDamageDealt": 0,
                "MagicDamageDealtToChampions": 0,
                "MagicDamageTaken": 0,
                "NeutralMinionsKilledTeamJungle": 0,
                "PentaKills": 3,
                "PhysicalDamageDealt": 0,
                "PhysicalDamageDealtToChampions": 30,
                "PhysicalDamageTaken": 0,
                "PlayerScore0": 1,
                "PlayerScore1": 7,
                "PlayerScore10": 0,
                "PlayerScore11": 0,
                "PlayerScore2": 236,
                "PlayerScore3": 0,
                "PlayerScore4": 1,
                "PlayerScore5": 1,
                "PlayerScore6": 20,
                "PlayerScore9": 0,
                "QuadraKills": 0,
                "Spell1Casts": 0,
                "Spell2Casts": 0,
                "Spell3Casts": 0,
                "Spell4Casts": 8170,
                "SummonerSpell1Casts": 0,
                "TimeCCOthers": 3,
                "TotalDamageDealtToChampions": 0,
                "TotalMinionsKilled": 0,
                "TripleKills": 0,
                "TrueDamageDealt": 1,
                "TrueDamageDealtToChampions": 82,
                "TrueDamageTaken": 9,
                "UnrealKills": 1,
                "VisionScore": 1,
                "WardsKilled": 107
            },
            "placement": 1,
            "players_eliminated": 3,
            "puuid": "AGuvUBuWy8OzdasyA-P793tPCgG7l1Us9GlI-RwCc0KzwkYrVGS-gx-amTbw4iYAGDip0K2oYNEg_Q",
            "time_eliminated": 2361.99072265625,
            "total_damage_to_players": 216,
            "traits": [
                {
                    "name": "TFT11_Arcanist",
                    "num_units": 2,
                    "style": 1,
                    "tier_current": 1,
                    "tier_total": 4
                },
                {
                    "name": "TFT11_Behemoth",
                    "num_units": 2,
                    "style": 1,
                    "tier_current": 1,
                    "tier_total": 3
                },
                {
                    "name": "TFT11_Dryad",
                    "num_units": 2,
                    "style": 1,
                    "tier_current": 1,
                    "tier_total": 3
                },
                {
                    "name": "TFT11_Fated",
                    "num_units": 7,
                    "style": 3,
                    "tier_current": 3,
                    "tier_total": 4
                },
                {
                    "name": "TFT11_Porcelain",
                    "num_units": 2,
                    "style": 1,
                    "tier_current": 1,
                    "tier_total": 3
                },
                {
                    "name": "TFT11_Reaper",
                    "num_units": 1,
                    "style": 0,
                    "tier_current": 0,
                    "tier_total": 2
                },
                {
                    "name": "TFT11_Sniper",
                    "num_units": 2,
                    "style": 1,
                    "tier_current": 1,
                    "tier_total": 3
                },
                {
                    "name": "TFT11_Umbral",
                    "num_units": 1,
                    "style": 0,
                    "tier_current": 0,
                    "tier_total": 4
                },
                {
                    "name": "TFT11_Warden",
                    "num_units": 2,
                    "style": 1,
                    "tier_current": 1,
                    "tier_total": 3
                }
            ],
            "units": [
                {
                    "character_id": "TFT11_Ahri",
                    "itemNames": [],
                    "name": "",
                    "rarity": 0,
                    "tier": 2
                },
                {
                    "character_id": "TFT11_Kindred",
                    "itemNames": [],
                    "name": "",
                    "rarity": 1,
                    "tier": 2
                },
                {
                    "character_id": "TFT11_Amumu",
                    "itemNames": [
                        "TFT_Item_Redemption"
                    ],
                    "name": "",
                    "rarity": 2,
                    "tier": 2
                },
                {
                    "character_id": "TFT11_Aphelios",
                    "itemNames": [
                        "TFT_Item_GuinsoosRageblade",
                        "TFT_Item_MadredsBloodrazor",
                        "TFT_Item_InfinityEdge"
                    ],
                    "name": "",
                    "rarity": 2,
                    "tier": 3
                },
                {
                    "character_id": "TFT11_Thresh",
                    "itemNames": [
                        "TFT_Item_BrambleVest",
                        "TFT_Item_NightHarvester",
                        "TFT_Item_WarmogsArmor"
                    ],
                    "name": "",
                    "rarity": 2,
                    "tier": 3
                },
                {
                    "character_id": "TFT11_Ashe",
                    "itemNames": [
                        "TFT_Item_GuinsoosRageblade",
                        "TFT11_Item_FatedEmblemItem",
                        "TFT_Item_LastWhisper"
                    ],
                    "name": "",
                    "rarity": 4,
                    "tier": 2
                },
                {
                    "character_id": "TFT11_Ornn",
                    "itemNames": [],
                    "name": "",
                    "rarity": 4,
                    "tier": 2
                },
                {
                    "character_id": "TFT11_Syndra",
                    "itemNames": [
                        "TFT_Item_SpearOfShojin",
                        "TFT_Item_Morellonomicon"
                    ],
                    "name": "",
                    "rarity": 4,
                    "tier": 2
                },
                {
                    "character_id": "TFT11_Sett",
                    "itemNames": [
                        "TFT_Item_ThiefsGloves",
                        "TFT_Item_DragonsClaw",
                        "TFT_Item_Deathblade"
                    ],
                    "name": "",
                    "rarity": 6,
                    "tier": 1
                }
            ]
        },
        {
            "augments": [
                "TFT10_Augment_Scapegoat",
                "TFT11_Augment_GoldenRemover",
                "TFT9_Augment_OldMansWalkingStick"
            ],
            "companion": {
                "content_ID": "127829e1-6a49-45f7-b59d-f63c3f8b6e58",
                "item_ID": 49003,
                "skin_ID": 3,
                "species": "PetChibiAhri"
            },
            "gold_left": 50,
            "last_round": 37,
            "level": 8,
            "missions": {
                "Assists": 0,
                "DamageDealt": 0,
                "DamageDealtToObjectives": 133176,
                "DamageDealtToTurrets": 4,
                "DamageTaken": 0,
                "Deaths": 16,
                "DoubleKills": 0,
                "GoldEarned": 0,
                "GoldSpent": 0,
                "InhibitorsDestroyed": 0,
                "KillingSprees": 13,
                "Kills": 0,
                "LargestKillingSpree": 68191,
                "LargestMultiKill": 133559,
                "MagicDamageDealt": 0,
                "MagicDamageDealtToChampions": 0,
                "MagicDamageTaken": 0,
                "NeutralMinionsKilledTeamJungle": 0,
                "PentaKills": 2,
                "PhysicalDamageDealt": 0,
                "PhysicalDamageDealtToChampions": 24,
                "PhysicalDamageTaken": 1,
                "PlayerScore0": 4,
                "PlayerScore1": 6,
                "PlayerScore10": 0,
                "PlayerScore11": 0,
                "PlayerScore2": 212,
                "PlayerScore3": 0,
                "PlayerScore4": 1,
                "PlayerScore5": 1,
                "PlayerScore6": 21,
                "PlayerScore9": 0,
                "QuadraKills": 0,
                "Spell1Casts": 0,
                "Spell2Casts": 0,
                "Spell3Casts": 0,
                "Spell4Casts": 9136,
                "SummonerSpell1Casts": 0,
                "TimeCCOthers": 0,
                "TotalDamageDealtToChampions": 0,
                "TotalMinionsKilled": 0,
                "TripleKills": 1,
                "TrueDamageDealt": 1,
                "TrueDamageDealtToChampions": 47,
                "TrueDamageTaken": 7,
                "UnrealKills": 1,
                "VisionScore": 0,
                "WardsKilled": 76
            },
            "placement": 4,
            "players_eliminated": 1,
            "puuid": "ls8UsSaX6I2G9pUV6OtgZTl1rTDd5DSV6-JfRGXwD6h3p_O6Gg5QoCbjfAGSqPlNUzu3UBFQYaSoNA",
            "time_eliminated": 2122.166015625,
            "total_damage_to_players": 117,
            "traits": [
                {
                    "name": "TFT11_Altruist",
                    "num_units": 2,
                    "style": 1,
                    "tier_current": 1,
                    "tier_total": 3
                },
                {
                    "name": "TFT11_Arcanist",
                    "num_units": 2,
                    "style": 1,
                    "tier_current": 1,
                    "tier_total": 4
                },
                {
                    "name": "TFT11_Artist",
                    "num_units": 1,
                    "style": 5,
                    "tier_current": 1,
                    "tier_total": 1
                },
                {
                    "name": "TFT11_Bruiser",
                    "num_units": 2,
                    "style": 1,
                    "tier_current": 1,
                    "tier_total": 4
                },
                {
                    "name": "TFT11_Fortune",
                    "num_units": 1,
                    "style": 0,
                    "tier_current": 0,
                    "tier_total": 3
                },
                {
                    "name": "TFT11_Heavenly",
                    "num_units": 2,
                    "style": 1,
                    "tier_current": 1,
                    "tier_total": 6
                },
                {
                    "name": "TFT11_Mythic",
                    "num_units": 5,
                    "style": 2,
                    "tier_current": 2,
                    "tier_total": 4
                },
                {
                    "name": "TFT11_Storyweaver",
                    "num_units": 3,
                    "style": 1,
                    "tier_current": 1,
                    "tier_total": 4
                },
                {
                    "name": "TFT11_Trickshot",
                    "num_units": 2,
                    "style": 1,
                    "tier_current": 1,
                    "tier_total": 2
                }
            ],
            "units": [
                {
                    "character_id": "TFT11_Sivir",
                    "itemNames": [],
                    "name": "",
                    "rarity": 0,
                    "tier": 2
                },
                {
                    "character_id": "TFT11_Neeko",
                    "itemNames": [],
                    "name": "",
                    "rarity": 1,
                    "tier": 2
                },
                {
                    "character_id": "TFT11_Riven",
                    "itemNames": [
                        "TFT11_Item_MythicEmblemItem",
                        "TFT_Item_NegatronCloak"
                    ],
                    "name": "",
                    "rarity": 1,
                    "tier": 2
                },
                {
                    "character_id": "TFT11_Bard",
                    "itemNames": [
                        "TFT_Item_GuinsoosRageblade",
                        "TFT_Item_HextechGunblade",
                        "TFT_Item_GuinsoosRageblade"
                    ],
                    "name": "",
                    "rarity": 2,
                    "tier": 3
                },
                {
                    "character_id": "TFT11_Soraka",
                    "itemNames": [
                        "TFT_Item_BlueBuff",
                        "TFT_Item_MadredsBloodrazor"
                    ],
                    "name": "",
                    "rarity": 2,
                    "tier": 2
                },
                {
                    "character_id": "TFT11_Zoe",
                    "itemNames": [
                        "TFT_Item_ThiefsGloves",
                        "TFT_Item_JeweledGauntlet",
                        "TFT_Item_ArchangelsStaff"
                    ],
                    "name": "",
                    "rarity": 2,
                    "tier": 3
                },
                {
                    "character_id": "TFT11_TahmKench",
                    "itemNames": [
                        "TFT_Item_NightHarvester",
                        "TFT_Item_WarmogsArmor",
                        "TFT_Item_RedBuff"
                    ],
                    "name": "",
                    "rarity": 2,
                    "tier": 3
                },
                {
                    "character_id": "TFT11_Hwei",
                    "itemNames": [],
                    "name": "",
                    "rarity": 6,
                    "tier": 1
                },
                {
                    "character_id": "TFT11_Kayle",
                    "itemNames": [
                        "TFT11_Storyweaver3_Support"
                    ],
                    "name": "",
                    "rarity": 9,
                    "tier": 1
                }
            ]
        }
    ],
    "queueId": 1100,
    "queue_id": 1100,
    "tft_game_type": "standard",
    "tft_set_core_name": "TFTSet11",
    "tft_set_number": 11
}